eigvals_multiplicity/__init__.py
eigvals_multiplicity/main.py
eigvals_multiplicity/py.typed
eigvals_multiplicity-0.0.0.dist-info/licenses/LICENSE
eigvals_multiplicity-0.0.0.dist-info/METADATA
eigvals_multiplicity-0.0.0.dist-info/WHEEL
eigvals_multiplicity-0.0.0.dist-info/top_level.txt
eigvals_multiplicity-0.0.0.dist-info/RECORD
