Metadata-Version: 2.4
Name: eigvals-multiplicity
Version: 0.0.0
Summary: Get and plot multiplicity of eigenvalues
Author-email: 34j <34j.95a2p@simplelogin.com>
License: MIT
Project-URL: Bug Tracker, https://github.com/34j/eigvals-multiplicity/issues
Project-URL: Changelog, https://github.com/34j/eigvals-multiplicity/blob/main/CHANGELOG.md
Project-URL: documentation, https://eigvals-multiplicity.readthedocs.io
Project-URL: repository, https://github.com/34j/eigvals-multiplicity
Classifier: Development Status :: 2 - Pre-Alpha
Classifier: Intended Audience :: Developers
Classifier: Natural Language :: English
Classifier: Operating System :: OS Independent
Classifier: Programming Language :: Python :: 3.9
Classifier: Programming Language :: Python :: 3.10
Classifier: Programming Language :: Python :: 3.11
Classifier: Programming Language :: Python :: 3.12
Classifier: Programming Language :: Python :: 3.13
Classifier: Topic :: Software Development :: Libraries
Requires-Python: >=3.9
License-File: LICENSE
Dynamic: license-file
